itglue/__init__.py
itglue/connection.py
itglue/path_processor.py
itglue/resources.py
itglue/utils.py
itglue/tests/__init__.py
itglue/tests/test_resource.py
itglue-0.2.0.dist-info/LICENSE.txt
itglue-0.2.0.dist-info/WHEEL
itglue-0.2.0.dist-info/METADATA
itglue-0.2.0.dist-info/RECORD
