Metadata-Version: 2.1
Name: itglue
Version: 0.2.0
Summary: A simple wrapper for the IT Glue API
Author-email: Ben Loyola <bloyola@itglue.com>
Maintainer-email: Ben Loyola <bloyola@itglue.com>, David Haymond <david@davidhaymond.dev>
Requires-Python: ~=3.6
Classifier: License :: OSI Approved :: MIT License
Requires-Dist: requests ~=2.22
Project-URL: Home, https://github.com/b-loyola/itglue-py
